Workbook

Sheet Base de Dados Original
A1: Numero Movimentacao | B1: Nome | C1: Município | D1: Data da Movimentacao | E1: Valor da Movimentação | F1: Tipo | G1: Banco | H1: Imagem | I1: Forma Pagamento
A2: 1 | B2: Caramuru Pie I | C2: São Paulo | D2: 43832 | E2: 675.87 | F2: Recebimento | G2: Itaú | H2: https://i.ibb.co/DznB5q4/Itau.png | I2: Pix
A3: 2 | B3: Indaia | C3: Belo Horizonte | D3: 43834 | E3: 1562555.9 | F3: Recebimento | G3: Nubank | H3: https://i.ibb.co/LpJM38D/Nubank.png | I3: Boleto
A4: 3 | B4: Diamante Iii | C4: São Paulo | D4: 43834 | E4: 4970.12 | F4: Recebimento | G4: Nubank | H4: https://i.ibb.co/LpJM38D/Nubank.png | I4: Boleto
A5: 4 | B5: Diamante Iii | C5: São Paulo | D5: 43834 | E5: 6716.79 | F5: Recebimento | G5: Nubank | H5: https://i.ibb.co/LpJM38D/Nubank.png | I5: Pix
A6: 5 | B6: Diamante Iii | C6: Vitória | D6: 43834 | E6: 7072.15 | F6: Recebimento | G6: Bradesco | H6: https://i.ibb.co/68RXB19/Bradesco.png | I6: MercadoPago
A7: 6 | B7: Canuelas | C7: São Paulo | D7: 43835 | E7: 6259.85 | F7: Recebimento | G7: Itaú | H7: https://i.ibb.co/DznB5q4/Itau.png | I7: Cartão
A8: 7 | B8: Indaia | C8: São Paulo | D8: 43835 | E8: 6720.29 | F8: Recebimento | G8: Bradesco | H8: https://i.ibb.co/68RXB19/Bradesco.png | I8: Pix
A9: 8 | B9: Libra Energia | C9: Rio De Janeiro | D9: 43835 | E9: 6510.7 | F9: Recebimento | G9: Bradesco | H9: https://i.ibb.co/68RXB19/Bradesco.png | I9: MercadoPago
A10: 9 | B10: Libra Energia | C10: Vitória | D10: 43835 | E10: 5882.06 | F10: Recebimento | G10: Itaú | H10: https://i.ibb.co/DznB5q4/Itau.png | I10: Pix
A11: 10 | B11: Libra Energia | C11: Rio De Janeiro | D11: 43835 | E11: 6712.31 | F11: Recebimento | G11: Itaú | H11: https://i.ibb.co/DznB5q4/Itau.png | I11: MercadoPago
A12: 11 | B12: Libra Energia | C12: Belo Horizonte | D12: 43835 | E12: 6583.79 | F12: Recebimento | G12: Itaú | H12: https://i.ibb.co/DznB5q4/Itau.png | I12: Pix
A13: 12 | B13: Libra Energia | C13: Rio De Janeiro | D13: 43835 | E13: 7066.01 | F13: Recebimento | G13: Nubank | H13: https://i.ibb.co/LpJM38D/Nubank.png | I13: Pix
... A2726: 2725 | B2726: Caramuru Pie I | C2726: Rio De Janeiro | D2726: 44558 | E2726: 9729.77 | F2726: Recebimento | G2726: Santander | H2726: https://i.ibb.co/zX8KX6R/Santander.png | I2726: Pix

Sheet Base de Dados
A1: Numero Movimentacao | B1: Nome | C1: Município | D1: Data da Movimentacao | E1: Mês | F1: Valor da Movimentação | G1: Tipo | H1: Banco | I1: Imagem | J1: Forma Pagamento
A2: 1 | B2: Caramuru Pie I | C2: São Paulo | D2: 43832 | E2: =TEXT(D2,"MMM") -> jan | F2: 675.87 | G2: Recebimento | H2: Itaú | I2: https://i.ibb.co/DznB5q4/Itau.png | J2: Pix
A3: 2 | B3: Indaia | C3: Belo Horizonte | D3: 43834 | E3: =TEXT(D3,"MMM") -> jan | F3: 1562555.9 | G3: Recebimento | H3: Nubank | I3: https://i.ibb.co/LpJM38D/Nubank.png | J3: Boleto
A4: 3 | B4: Diamante Iii | C4: São Paulo | D4: 43834 | E4: =TEXT(D4,"MMM") -> jan | F4: 4970.12 | G4: Recebimento | H4: Nubank | I4: https://i.ibb.co/LpJM38D/Nubank.png | J4: Boleto
A5: 4 | B5: Diamante Iii | C5: São Paulo | D5: 43834 | E5: =TEXT(D5,"MMM") -> jan | F5: 6716.79 | G5: Recebimento | H5: Nubank | I5: https://i.ibb.co/LpJM38D/Nubank.png | J5: Pix
A6: 5 | B6: Diamante Iii | C6: Vitória | D6: 43834 | E6: =TEXT(D6,"MMM") -> jan | F6: 7072.15 | G6: Recebimento | H6: Bradesco | I6: https://i.ibb.co/68RXB19/Bradesco.png | J6: MercadoPago
A7: 6 | B7: Canuelas | C7: São Paulo | D7: 43835 | E7: =TEXT(D7,"MMM") -> jan | F7: 6259.85 | G7: Recebimento | H7: Itaú | I7: https://i.ibb.co/DznB5q4/Itau.png | J7: Cartão
A8: 7 | B8: Indaia | C8: São Paulo | D8: 43835 | E8: =TEXT(D8,"MMM") -> jan | F8: 6720.29 | G8: Recebimento | H8: Bradesco | I8: https://i.ibb.co/68RXB19/Bradesco.png | J8: Pix
A9: 8 | B9: Libra Energia | C9: Rio De Janeiro | D9: 43835 | E9: =TEXT(D9,"MMM") -> jan | F9: 6510.7 | G9: Recebimento | H9: Bradesco | I9: https://i.ibb.co/68RXB19/Bradesco.png | J9: MercadoPago
A10: 9 | B10: Libra Energia | C10: Vitória | D10: 43835 | E10: =TEXT(D10,"MMM") -> jan | F10: 5882.06 | G10: Recebimento | H10: Itaú | I10: https://i.ibb.co/DznB5q4/Itau.png | J10: Pix
A11: 10 | B11: Libra Energia | C11: Rio De Janeiro | D11: 43835 | E11: =TEXT(D11,"MMM") -> jan | F11: 6712.31 | G11: Recebimento | H11: Itaú | I11: https://i.ibb.co/DznB5q4/Itau.png | J11: MercadoPago
A12: 11 | B12: Libra Energia | C12: Belo Horizonte | D12: 43835 | E12: =TEXT(D12,"MMM") -> jan | F12: 6583.79 | G12: Recebimento | H12: Itaú | I12: https://i.ibb.co/DznB5q4/Itau.png | J12: Pix
A13: 12 | B13: Libra Energia | C13: Rio De Janeiro | D13: 43835 | E13: =TEXT(D13,"MMM") -> jan | F13: 7066.01 | G13: Recebimento | H13: Nubank | I13: https://i.ibb.co/LpJM38D/Nubank.png | J13: Pix
... A15: 14 | B15: Indaia | C15: Rio De Janeiro | D15: 43836 | E15: =TEXT(D15,"MMM") -> jan | F15: 12261.57 | G15: Recebimento | H15: Itaú | I15: https://i.ibb.co/DznB5q4/Itau.png | J15: Pix
A16: 15 | B16: Indaia | C16: Belo Horizonte | D16: 43836 | E16: =TEXT(D16,"MMM") -> jan | F16: 12769.64 | H16: Safra | I16: https://i.ibb.co/FhY6B5f/Safra.png | J16: Pix
A17: 16 | B17: Elkem Carboderivados | C17: Belo Horizonte | D17: 43836 | E17: =TEXT(D17,"MMM") -> jan | F17: 13544.81 | G17: Recebimento | H17: Itaú | I17: https://i.ibb.co/DznB5q4/Itau.png | J17: Boleto
A18: 17 | B18: Elkem Carboderivados | C18: Belo Horizonte | D18: 43836 | E18: =TEXT(D18,"MMM") -> jan | F18: 453183.64 | G18: Recebimento | H18: Nubank | I18: https://i.ibb.co/LpJM38D/Nubank.png | J18: Pix
A19: 18 | B19: Tempo Energia | C19: Vitória | D19: 43836 | E19: =TEXT(D19,"MMM") -> jan | F19: -1584.35 | G19: Pagamento | H19: Itaú | I19: https://i.ibb.co/DznB5q4/Itau.png | J19: Pix
A20: 19 | B20: Tenneco | C20: Belo Horizonte | D20: 43836 | E20: =TEXT(D20,"MMM") -> jan | F20: 29823.06 | G20: Recebimento | H20: Itaú | I20: https://i.ibb.co/DznB5q4/Itau.png | J20: Pix
A21: 20 | B21: Tempo Energia | C21: Rio De Janeiro | D21: 43836 | E21: =TEXT(D21,"MMM") -> jan | F21: 24967.63 | G21: Recebimento | H21: Bradesco | I21: https://i.ibb.co/68RXB19/Bradesco.png | J21: Cartão
A22: 21 | B22: Tenneco | C22: São Paulo | D22: 43836 | E22: =TEXT(D22,"MMM") -> jan | F22: 27617.04 | G22: Recebimento | H22: Nubank | I22: https://i.ibb.co/LpJM38D/Nubank.png | J22: Pix
A23: 22 | B23: Tempo Energia | C23: Belo Horizonte | D23: 43836 | E23: =TEXT(D23,"MMM") -> jan | F23: 28136.57 | G23: Recebimento | H23: Santander | I23: https://i.ibb.co/zX8KX6R/Santander.png | J23: Pix
A24: 23 | B24: Tenneco | C24: Vitória | D24: 43836 | E24: =TEXT(D24,"MMM") -> jan | F24: 23719.25 | G24: Recebimento | H24: Santander | I24: https://i.ibb.co/zX8KX6R/Santander.png | J24: MercadoPago
A25: 24 | B25: Tempo Energia | C25: São Paulo | D25: 43836 | E25: =TEXT(D25,"MMM") -> jan | F25: 24473.54 | G25: Recebimento | H25: Nubank | I25: https://i.ibb.co/LpJM38D/Nubank.png | J25: Pix
A26: 25 | B26: Tenneco | C26: Belo Horizonte | D26: 43836 | E26: =TEXT(D26,"MMM") -> jan | F26: -268.56 | G26: Pagamento | H26: Itaú | I26: https://i.ibb.co/DznB5q4/Itau.png | J26: Cartão
A27: 26 | B27: Tempo Energia | C27: Belo Horizonte | D27: 43836 | E27: =TEXT(D27,"MMM") -> jan | F27: -52492.86 | G27: Pagamento | H27: Itaú | I27: https://i.ibb.co/DznB5q4/Itau.png | J27: Pix
A28: 27 | B28: Tenneco | C28: Belo Horizonte | D28: 43836 | E28: =TEXT(D28,"MMM") -> jan | F28: 29336.04 | G28: Recebimento | H28: Nubank | I28: https://i.ibb.co/LpJM38D/Nubank.png | J28: Cartão
... A2726: 2725 | B2726: Caramuru Pie I | C2726: Rio De Janeiro | D2726: 44558 | E2726: =TEXT(D2726,"MMM") -> dez | F2726: 9729.77 | G2726: Recebimento | H2726: Santander | I2726: https://i.ibb.co/zX8KX6R/Santander.png | J2726: Pix

Sheet Analise de Dados
A1: Tipo | B1: Soma - Valor da Movimentação | D1: Tipo | E1: Soma - Valor da Movimentação | G1: Margem de Lucro | I1: Complemento de Marge de Lucro
A2: Recebimento | B2: 94602867 | D2: Pagamento | E2: -44863841 | G2: =E6/B3 -> 0.37576658 | I2: =1 - G2 -> 0.62423342
A3: Total Resultado | B3: 94602867 | D3: Total Resultado | E3: -44863841 | F3: =-(E3) -> 44863841
B5: Impostos | E5: Lucro
B6: =B3*0.15 -> 14190430 | E6: =-(B6-B3-E3) -> 35548596 | G6: Imagem | H6: (vazio)
G7: https://i.ibb.co/68RXB19/Bradesco.png
A8: Soma - Valor da Movimentação | B8: Tipo | G8: https://i.ibb.co/DznB5q4/Itau.png
A9: Mês | B9: Pagamento | C9: Recebimento | D9: Imposto | E9: Lucro por Mês | G9: https://i.ibb.co/FhY6B5f/Safra.png
A10: jan | B10: -2704018.1 | C10: 8714901.9 | D10: =C10*0.15 -> 1307235.3 | E10: =-(D10-C10-B10) -> 4703648.6 | G10: https://i.ibb.co/LpJM38D/Nubank.png
A11: fev | B11: -1871936.3 | C11: 9839798.3 | D11: =C11*0.15 -> 1475969.7 | E11: =-(D11-C11-B11) -> 6491892.2 | G11: https://i.ibb.co/zX8KX6R/Santander.png
A12: mar | B12: -1746141.9 | C12: 13545042 | D12: =C12*0.15 -> 2031756.3 | E12: =-(D12-C12-B12) -> 9767143.6
A13: abr | B13: -9004149.5 | C13: 7062871.7 | D13: =C13*0.15 -> 1059430.7 | E13: =-(D13-C13-B13) -> -3000708.6
A14: mai | B14: -924971.28 | C14: 6645410.6 | D14: =C14*0.15 -> 996811.59 | E14: =-(D14-C14-B14) -> 4723627.7
A15: jun | B15: -9682075.2 | C15: 5367923.7 | D15: =C15*0.15 -> 805188.56 | E15: =-(D15-C15-B15) -> -5119340.1 | G15: Qtd Movimentações
A16: jul | B16: -2950657 | C16: 4558223.7 | D16: =C16*0.15 -> 683733.55 | E16: =-(D16-C16-B16) -> 923833.08 | G16: =COUNTA('Base de Dados'!F2:F2726) -> 2725
A17: ago | B17: -8145847 | C17: 5483890.5 | D17: =C17*0.15 -> 822583.57 | E17: =-(D17-C17-B17) -> -3484540
A18: set | B18: -3255770.7 | C18: 18567194 | D18: =C18*0.15 -> 2785079.1 | E18: =-(D18-C18-B18) -> 12526344 | G18: Movimentações PIX
A19: out | B19: -1553847.8 | C19: 5332314.1 | D19: =C19*0.15 -> 799847.11 | E19: =-(D19-C19-B19) -> 2978619.2 | G19: =COUNTIF('Base de Dados'!J2:J2726, "PIX") -> 1200
A20: nov | B20: -1566919.8 | C20: 5834003 | D20: =C20*0.15 -> 875100.45 | E20: =-(D20-C20-B20) -> 3391982.8
A21: dez | B21: -1457506.4 | C21: 3651293.5 | D21: =C21*0.15 -> 547694.03 | E21: =-(D21-C21-B21) -> 1646093.1 | G21: % PIX
A22: Total Resultado | B22: -44863841 | C22: 94602867 | D22: =C22*0.15 -> 14190430 | E22: =-(D22-C22-B22) -> 35548596 | G22: =G19/G16 -> 0.44036697

Sheet Dashboard
C2: Recebimentos | E2: Pagamentos | G2: Imposto | I2: Lucro
C3: ='Analise de Dados'!B3 -> 94602867 | E3: ='Analise de Dados'!F3 -> 44863841 | G3: ='Analise de Dados'!B6 -> 14190430 | I3: ='Analise de Dados'!E6 -> 35548596
H6: Movimentações | I6: ='Analise de Dados'!G16 -> 2725
H7: Por PIX | I7: ='Analise de Dados'!G19 -> 1200
H8: % | I8: ='Analise de Dados'!G22 -> 0.44036697
F11: Marge Lucro
F12: ='Analise de Dados'!G2 -> 0.37576658
